nanonis.py
nanonis-1.0.5.dist-info/METADATA
nanonis-1.0.5.dist-info/WHEEL
nanonis-1.0.5.dist-info/RECORD
