Metadata-Version: 2.3
Name: nanonis
Version: 1.0.5
Summary: python module for treating nanonis data
License: MIT
Author: stefanotriv
Author-email: stm@nanogune.eu
Requires-Python: >=3.9,<4.0
Classifier: License :: OSI Approved :: MIT License
Classifier: Programming Language :: Python :: 3
Classifier: Programming Language :: Python :: 3.9
Classifier: Programming Language :: Python :: 3.10
Classifier: Programming Language :: Python :: 3.11
Classifier: Programming Language :: Python :: 3.12
Classifier: Programming Language :: Python :: 3.13
Project-URL: Homepage, https://github.com/nanogunecic09/nanonis
